ClojureRumenjiaocheng/README.md
ClojureRumenjiaocheng/__init__.py
ClojureRumenjiaocheng/__main__.py
ClojureRumenjiaocheng/file.epub
ClojureRumenjiaocheng/index.html
ClojureRumenjiaocheng/css/__init__.py
ClojureRumenjiaocheng/css/annotations.css
ClojureRumenjiaocheng/css/main.css
ClojureRumenjiaocheng/css/normalize.css
ClojureRumenjiaocheng/css/popup.css
ClojureRumenjiaocheng/font/__init__.py
ClojureRumenjiaocheng/font/fontello.eot
ClojureRumenjiaocheng/font/fontello.svg
ClojureRumenjiaocheng/font/fontello.ttf
ClojureRumenjiaocheng/font/fontello.woff
ClojureRumenjiaocheng/img/__init__.py
ClojureRumenjiaocheng/img/annotator-glyph-sprite.png
ClojureRumenjiaocheng/img/annotator-icon-sprite.png
ClojureRumenjiaocheng/img/apple-touch-icon.png
ClojureRumenjiaocheng/img/cancelfullscreen.png
ClojureRumenjiaocheng/img/close.png
ClojureRumenjiaocheng/img/fullscreen.png
ClojureRumenjiaocheng/img/loader.gif
ClojureRumenjiaocheng/img/menu-icon.png
ClojureRumenjiaocheng/img/save.png
ClojureRumenjiaocheng/img/saved.png
ClojureRumenjiaocheng/img/settings-s.png
ClojureRumenjiaocheng/img/settings.png
ClojureRumenjiaocheng/img/star.png
ClojureRumenjiaocheng/js/__init__.py
ClojureRumenjiaocheng/js/epub.js
ClojureRumenjiaocheng/js/epub.min.js
ClojureRumenjiaocheng/js/epub.min.map
ClojureRumenjiaocheng/js/hooks.min.js
ClojureRumenjiaocheng/js/hooks.min.map
ClojureRumenjiaocheng/js/reader.js
ClojureRumenjiaocheng/js/reader.js.map
ClojureRumenjiaocheng/js/reader.min.js
ClojureRumenjiaocheng/js/reader.min.map
ClojureRumenjiaocheng/js/hooks/__init__.py
ClojureRumenjiaocheng/js/hooks/extensions/__init__.py
ClojureRumenjiaocheng/js/hooks/extensions/highlight.js
ClojureRumenjiaocheng/js/libs/__init__.py
ClojureRumenjiaocheng/js/libs/jquery.min.js
ClojureRumenjiaocheng/js/libs/localforage.min.js
ClojureRumenjiaocheng/js/libs/screenfull.js
ClojureRumenjiaocheng/js/libs/screenfull.min.js
ClojureRumenjiaocheng/js/libs/zip.min.js
ClojureRumenjiaocheng/js/plugins/__init__.py
clojure_rumenjiaocheng-2024.3.1.0.dist-info/METADATA
clojure_rumenjiaocheng-2024.3.1.0.dist-info/WHEEL
clojure_rumenjiaocheng-2024.3.1.0.dist-info/entry_points.txt
clojure_rumenjiaocheng-2024.3.1.0.dist-info/top_level.txt
clojure_rumenjiaocheng-2024.3.1.0.dist-info/RECORD
